finitelycomputable/finitelycomputable_env_info.py
finitelycomputable_env_info-25.7.dist-info/METADATA
finitelycomputable_env_info-25.7.dist-info/WHEEL
finitelycomputable_env_info-25.7.dist-info/top_level.txt
finitelycomputable_env_info-25.7.dist-info/RECORD
